wxcbench/__init__.py
wxcbench/py.typed
wxcbench/aviation_turbulence/__init__.py
wxcbench/aviation_turbulence/config.py
wxcbench/aviation_turbulence/convert2risk_map.py
wxcbench/aviation_turbulence/grid_pireps.py
wxcbench/aviation_turbulence/make_training_data.py
wxcbench/aviation_turbulence/modg_preprocess.py
wxcbench/aviation_turbulence/pirep_downloads.py
wxcbench/aviation_turbulence/turb_eda_preprocessing.py
wxcbench/forecast_report_generation/__init__.py
wxcbench/forecast_report_generation/config.py
wxcbench/forecast_report_generation/create_metadata.py
wxcbench/forecast_report_generation/download_hrrr.py
wxcbench/forecast_report_generation/weather_report_data_scraping.py
wxcbench/hurricane/__init__.py
wxcbench/hurricane/config.py
wxcbench/hurricane/hurricane_intensity.py
wxcbench/hurricane/hurricane_track.py
wxcbench/long_term_precipitation_forecast/__init__.py
wxcbench/long_term_precipitation_forecast/config.py
wxcbench/long_term_precipitation_forecast/data_loading.py
wxcbench/long_term_precipitation_forecast/evaluation.py
wxcbench/long_term_precipitation_forecast/preprocessing.py
wxcbench/long_term_precipitation_forecast/visualization.py
wxcbench/nonlocal_parameterization/__init__.py
wxcbench/nonlocal_parameterization/coarsegrain_fluxes.py
wxcbench/nonlocal_parameterization/compute_momentum_flux.py
wxcbench/nonlocal_parameterization/config.py
wxcbench/nonlocal_parameterization/download_era5.py
wxcbench/weather_analog/__init__.py
wxcbench/weather_analog/config.py
wxcbench/weather_analog/preprocess_weather_analog.py
wxcbench-0.1.6.dist-info/licenses/LICENSE
wxcbench-0.1.6.dist-info/METADATA
wxcbench-0.1.6.dist-info/WHEEL
wxcbench-0.1.6.dist-info/top_level.txt
wxcbench-0.1.6.dist-info/RECORD
