Metadata-Version: 2.4
Name: wxcbench
Version: 0.1.6
Summary: A multi-modal dataset toolkit for weather and climate downstream tasks
Author-email: Prajun Trital <prajuncs@gmail.com>
License: LICENSE
Project-URL: Homepage, https://github.com/prajun7/wxc-bench-package
Project-URL: Documentation, https://github.com/prajun7/wxc-bench-package#readme
Project-URL: Repository, https://github.com/prajun7/wxc-bench-package
Project-URL: Bug Reports, https://github.com/prajun7/wxc-bench-package/issues
Keywords: weather,climate,machine-learning,dataset,turbulence,hurricane,precipitation,forecast,atmospheric-science,earth-science,pirep,hrrr,era5,merra2
Classifier: Development Status :: 4 - Beta
Classifier: Intended Audience :: Developers
Classifier: Intended Audience :: Science/Research
Classifier: Topic :: Software Development :: Libraries :: Python Modules
Classifier: Topic :: Scientific/Engineering :: Atmospheric Science
Classifier: Topic :: Scientific/Engineering :: Artificial Intelligence
Classifier: License :: OSI Approved :: MIT License
Classifier: Programming Language :: Python :: 3
Classifier: Programming Language :: Python :: 3.8
Classifier: Programming Language :: Python :: 3.9
Classifier: Programming Language :: Python :: 3.10
Classifier: Programming Language :: Python :: 3.11
Classifier: Programming Language :: Python :: 3.12
Classifier: Operating System :: OS Independent
Requires-Python: >=3.8
License-File: LICENSE
Requires-Dist: numpy>=1.20.0
Requires-Dist: pandas>=1.3.0
Requires-Dist: xarray>=0.19.0
Requires-Dist: netcdf4>=1.5.7
Requires-Dist: matplotlib>=3.3.0
Requires-Dist: requests>=2.25.0
Requires-Dist: beautifulsoup4>=4.9.0
Requires-Dist: setuptools>=61.0
Requires-Dist: scipy>=1.1.0
Requires-Dist: scikit-learn>=0.24.0
Requires-Dist: cartopy>=0.21.0
Requires-Dist: tropycal>=0.5.0
Requires-Dist: xesmf>=0.6.0
Requires-Dist: cdsapi>=0.5.0
Provides-Extra: nonlocal-parameterization
Requires-Dist: windspharm>=1.7.0; extra == "nonlocal-parameterization"
Dynamic: license-file
